WebServerService/__init__.py
WebServerService/__main__.py
WebServerService/const.py
WebServerService/service copy.py
WebServerService/service.py
pih_web-1.18.dist-info/METADATA
pih_web-1.18.dist-info/WHEEL
pih_web-1.18.dist-info/entry_points.txt
pih_web-1.18.dist-info/top_level.txt
pih_web-1.18.dist-info/RECORD
