Metadata-Version: 2.1
Name: pih-web
Version: 1.18
Summary: PIH Web Server service package
Home-page: https://pacifichosp.com/
Author: Nikita Karachentsev
Author-email: it@pacifichosp.com
License: MIT
Requires-Dist: ipih
Requires-Dist: fastapi
Requires-Dist: uvicorn
Requires-Dist: python-multipart
Requires-Dist: dicttoxml
